training_telemetry/__init__.py
training_telemetry/config.py
training_telemetry/config_loader.py
training_telemetry/context.py
training_telemetry/duration.py
training_telemetry/events.py
training_telemetry/internal/__init__.py
training_telemetry/internal/backend.py
training_telemetry/internal/backends/__init__.py
training_telemetry/internal/backends/event_based_backend.py
training_telemetry/internal/backends/file_backend.py
training_telemetry/internal/backends/logger_backend.py
training_telemetry/internal/backends/nvtx_backend.py
training_telemetry/internal/backends/otlp_logs_backend.py
training_telemetry/internal/backends/otlp_traces_backend.py
training_telemetry/internal/backends/record_type.py
training_telemetry/internal/standard_recorder.py
training_telemetry/metrics.py
training_telemetry/provider.py
training_telemetry/recorder.py
training_telemetry/spans.py
training_telemetry/torch/__init__.py
training_telemetry/torch/example.py
training_telemetry/torch/example_config.yaml
training_telemetry/torch/utils.py
training_telemetry/utils.py
training_telemetry/verbosity.py
training_telemetry/version.py
aidot_training_telemetry-1.1.0.dist-info/LICENSE
aidot_training_telemetry-1.1.0.dist-info/METADATA
aidot_training_telemetry-1.1.0.dist-info/WHEEL
aidot_training_telemetry-1.1.0.dist-info/RECORD
