Metadata-Version: 2.3
Name: aidot-training-telemetry
Version: 1.1.0
Summary: Utilities for monitoring training of large foundation models
License: NVIDIA Mission Control, License no 744-SW7001+P1CMI36
Author: Stefania Alborghetti
Author-email: salborghetti@nvidia.com
Requires-Python: >=3.10
Classifier: Development Status :: 3 - Alpha
Classifier: Environment :: Console
Classifier: Intended Audience :: Developers
Classifier: Intended Audience :: Information Technology
Classifier: Intended Audience :: Science/Research
Classifier: License :: OSI Approved :: Apache Software License
Classifier: Natural Language :: English
Classifier: Operating System :: OS Independent
Classifier: Programming Language :: Python :: 3
Classifier: Programming Language :: Python :: 3.10
Classifier: Programming Language :: Python :: 3.11
Classifier: Programming Language :: Python :: 3.12
Classifier: Topic :: Scientific/Engineering :: Artificial Intelligence
Classifier: Topic :: Scientific/Engineering
Classifier: Topic :: Software Development :: Libraries :: Python Modules
Classifier: Topic :: Software Development :: Libraries
Classifier: Topic :: Utilities
Provides-Extra: ai-tools
Requires-Dist: numpy (>=1.24.0,<3.0.0) ; extra == "ai-tools"
Requires-Dist: nvtx (>=0.2.5,<1.0.0)
Requires-Dist: opentelemetry-api (>=1.27.0,<2.0.0)
Requires-Dist: opentelemetry-exporter-otlp-proto-grpc (>=1.27.0,<2.0.0)
Requires-Dist: opentelemetry-exporter-otlp-proto-http (>=1.27.0,<2.0.0)
Requires-Dist: opentelemetry-sdk (>=1.27.0,<2.0.0)
Requires-Dist: pyyaml (>=6.0.2,<7.0.0)
Requires-Dist: torch (>=2.7.1,<3.0.0) ; extra == "ai-tools"
Requires-Dist: tzlocal (>=5.3,<6.0)
